feed_media_backup/__init__.py
feed_media_backup/cli.py
feed_media_backup/utils.py
feed_media_backup-0.0.3.dist-info/DESCRIPTION.rst
feed_media_backup-0.0.3.dist-info/METADATA
feed_media_backup-0.0.3.dist-info/RECORD
feed_media_backup-0.0.3.dist-info/WHEEL
feed_media_backup-0.0.3.dist-info/entry_points.txt
feed_media_backup-0.0.3.dist-info/metadata.json
feed_media_backup-0.0.3.dist-info/top_level.txt
