Metadata-Version: 2.0
Name: feed-media-backup
Version: 0.0.3
Summary: Backups media from blog RSS feeds.
Home-page: https://github.com/xsteadfastx/feed_media_backup
Author: Marvin Steadfast
Author-email: marvin@xsteadfastx.org
License: MIT
Platform: UNKNOWN
Classifier: License :: OSI Approved :: MIT License
Classifier: Programming Language :: Python
Classifier: Programming Language :: Python :: 3.4
Classifier: Programming Language :: Python :: 3.5
Classifier: Programming Language :: Python :: 3.6
Requires-Dist: beautifulsoup4 (>=4.6.0)
Requires-Dist: click (>=6.7)
Requires-Dist: feedparser (>=5.2.1)
Requires-Dist: logzero (>=1.3.0)
Requires-Dist: lxml (>=3.8.0)
Requires-Dist: tinydb (>=3.4.0)
Requires-Dist: typing (>=3.6.2)
Requires-Dist: youtube-dl (>=2017.8.18)
